Workbook

Sheet Editable Inputs
A1: INPUT / ASSUMPTION | B1: VALUE | C1: UNIT | D1: EVIDENCE STATUS
A2: Two-phase cumulative residents | B2: 787934 | C2: people | D2: Author supplied planning population
A3: Phase 1 fraction | B3: 0.5 | C3: fraction | D3: 50% assumed; phase breakdown unverified
A4: Residents per household | B4: 2.4 | C4: persons | D4: Statistics Canada B.C. 2021 census
A5: Vehicle provision eligibility | B5: 0.9 | C5: share of households | D5: Hypothetical optional provision
A6: Acquisition cost per EV | B6: 38000 | C6: CAD | D6: Illustrative; not a vendor quote
A7: Replacement cycle | B7: 12 | C7: years | D7: Illustrative
A8: Vehicle financing rate | B8: 0.05 | C8: annual fraction | D8: Illustrative
A9: Free EV charging participation | B9: 0.85 | C9: share of households | D9: Illustrative
A10: Annual distance | B10: 12000 | C10: km per EV | D10: Illustrative
A11: EV energy at battery | B11: 0.19 | C11: kWh/km | D11: Illustrative
A12: Charging losses | B12: 0.1 | C12: fraction of metered energy | D12: Illustrative; charger electricity / (1-loss)
A13: Equivalent public charging value | B13: 0.35 | C13: CAD/kWh | D13: Illustrative between B.C. Hydro 2026 charger rates
... A24: Food fulfilment cost fraction | B24: 0.65 | C24: fraction of market value | D24: Illustrative, not audited
A25: Eligible agricultural fuel (8 regional district baseline) | B25: ='RD Agriculture'!L10 | C25: L/year | D25: 2021 census areas times scenario machinery fuel intensities, NOT measured municipal sales. See RD Agriculture.
A26: Eligible other renewable fuel | B26: 180000000 | C26: L/year | D26: Unverified proposed volume
A27: Agricultural renewable-fossil gap | B27: 0.25 | C27: CAD/L | D27: Scenario differential; must be tested
A28: Other renewable-fossil gap | B28: 0.18 | C28: CAD/L | D28: Scenario differential; must be tested
A29: Eligible fruit in drying discount | B29: 5000 | C29: tonnes/year | D29: Illustrative
A30: Dryer service discount | B30: 25 | C30: CAD/tonne | D30: Illustrative
A31: Mature community target | B31: 4600000000 | C31: CAD/year | D31: Proponent aspiration; not financed
A32: Installed IT power | B32: 3624.51 | C32: MW IT | D32: Digital Gardens mature concept
A33: Heat capture from operating IT | B33: 0.85 | C33: fraction | D33: Author assumption
A34: Potential use of captured heat | B34: 0.6 | C34: fraction | D34: Author assumption
A35: Electricity CO2 intensity | B35: 50 | C35: kg CO2e/MWh | D35: Scenario only
A36: Marketable fresh-produce fraction | B36: 0.9 | C36: fraction of greenhouse gross harvest | D36: Screening assumption for grade and loss; not measured
A37: Marketable seafood yield fraction | B37: 0.65 | C37: fraction of whole aquaculture live weight | D37: Illustrative edible market-product recovery; species mix matters

Sheet Two-phase Benefits
A1: ANNUAL BENEFIT COMPONENT | B1: PHASE 1 (CALC) | C1: PHASE 2 (CALC) | D1: MODEL BOUNDARY / NOTE
A2: Population (cumulative) | B2: ='Editable Inputs'!$B$2*'Editable Inputs'!$B$3 | C2: ='Editable Inputs'!$B$2*1 | D2: Two phases are cumulative, not additive populations.
A3: Households | B3: =B2/'Editable Inputs'!$B$4 | C3: =C2/'Editable Inputs'!$B$4 | D3: B.C. 2021 census 2.4 residents per household.
A4: Eligible provisioned EVs | B4: =B3*'Editable Inputs'!$B$5 | C4: =C3*'Editable Inputs'!$B$5 | D4: Optional vehicle provision, not confirmed.
A5: Free-charging EVs | B5: =B3*'Editable Inputs'!$B$9 | C5: =C3*'Editable Inputs'!$B$9 | D5: Free charging only; not household electricity.
A6: EV public charging GWh/year | B6: =B5*'Editable Inputs'!$B$10*'Editable Inputs'!$B$11/(1-'Editable Inputs'!$B$12)/1000000 | C6: =C5*'Editable Inputs'!$B$10*'Editable Inputs'!$B$11/(1-'Editable Inputs'!$B$12)/1000000 | D6: This is electricity bought/provided to chargers; must add to grid load.
A7: Mean EV charging MW | B7: =B6*1000/8760 | C7: =C6*1000/8760 | D7: Annual average; not a transmission interconnection study.
A8: Conditional coincident EV charging MW | B8: =B5*'Editable Inputs'!$B$16*'Editable Inputs'!$B$17/1000 | C8: =C5*'Editable Inputs'!$B$16*'Editable Inputs'!$B$17/1000 | D8: 6% simultaneity proxy, not hourly dispatch.
A9: EV fleet value annual equivalent CAD m | B9: =B4*'Editable Inputs'!$B$6/'Editable Inputs'!$B$7/1000000 | C9: =C4*'Editable Inputs'!$B$6/'Editable Inputs'!$B$7/1000000 | D9: Straight-line asset value, not a yearly cash transfer.
A10: EV fleet financing annual CAD m | B10: =B4*'Editable Inputs'!$B$6*('Editable Inputs'!$B$8*(1+'Editable Inputs'!$B$8)^'Editable Inputs'!$B$7)/((1+'Editable Inputs'!$B$8)^'Editable Inputs'!$B$7-1)/1000000 | C10: =C4*'Editable Inputs'!$B$6*('Editable Inputs'!$B$8*(1+'Editable Inputs'!$B$8)^'Editable Inputs'!$B$7)/((1+'Editable Inputs'!$B$8)^'Editable Inputs'!$B$7-1)/1000000 | D10: 5% annuity over 12 years; annual funding differs from value.
A11: Charging retail-equivalent value CAD m | B11: =B6*'Editable Inputs'!$B$13 | C11: =C6*'Editable Inputs'!$B$13 | D11: Retail-equivalent free charging service value.
A12: Charging electricity+operations cost CAD m | B12: =B6*('Editable Inputs'!$B$14+'Editable Inputs'!$B$15) | C12: =C6*('Editable Inputs'!$B$14+'Editable Inputs'!$B$15) | D12: Costs are illustrative energy + operations, excluding infrastructure.
A13: Greenhouse food market value CAD m | B13: =B2*'Editable Inputs'!$B$19*'Editable Inputs'!$B$20/1000000 | C13: =C2*'Editable Inputs'!$B$19*'Editable Inputs'!$B$20/1000000 | D13: 146 kg/year per resident at assumed produce price; conditional.
A14: Seafood market value CAD m | B14: =B2*'Editable Inputs'!$B$22*'Editable Inputs'!$B$23/1000000 | C14: =C2*'Editable Inputs'!$B$22*'Editable Inputs'!$B$23/1000000 | D14: 46 kg/year per resident at assumed seafood price; conditional.
A15: Agriculture fuel price-parity subsidy CAD m | B15: ='Editable Inputs'!$B$25*MAX(0,'Editable Inputs'!$B$27)*(B2/'Editable Inputs'!$B$2)/1000000 | C15: ='Editable Inputs'!$B$25*MAX(0,'Editable Inputs'!$B$27)*(C2/'Editable Inputs'!$B$2)/1000000 | D15: max(0, renewable landed price - fossil parity)*L.
A16: Other fuel price-parity subsidy CAD m | B16: ='Editable Inputs'!$B$26*MAX(0,'Editable Inputs'!$B$28)*(B2/'Editable Inputs'!$B$2)/1000000 | C16: ='Editable Inputs'!$B$26*MAX(0,'Editable Inputs'!$B$28)*(C2/'Editable Inputs'!$B$2)/1000000 | D16: No subsidy if renewable cheaper than fossil.
A17: Fruit-dryer farmer discount CAD m | B17: ='Editable Inputs'!$B$29*'Editable Inputs'!$B$30*(B2/'Editable Inputs'!$B$2)/1000000 | C17: ='Editable Inputs'!$B$29*'Editable Inputs'!$B$30*(C2/'Editable Inputs'!$B$2)/1000000 | D17: Farmer discount, not total producer revenue.
A18: Household-electricity benefits CAD m | B18: =0 | C18: =0 | D18: Always ZERO: no free domestic electricity.
A19: TOTAL market-equivalent annual value CAD m | B19: =SUM(B9,B11,B13:B18) | C19: =SUM(C9,C11,C13:C18) | D19: Sum annualised EV value, charging, food, and parity.
A20: TOTAL illustrative annual financing CAD m | B20: =SUM(B10,B12,B13*'Editable Inputs'!$B$24,B14*'Editable Inputs'!$B$24,B15:B17) | C20: =SUM(C10,C12,C13*'Editable Inputs'!$B$24,C14*'Editable Inputs'!$B$24,C15:C17) | D20: Includes financed EV capital and programme cost of services.
A21: Difference to CAD 4.6B aspirational target CAD m | B21: =MAX(0,'Editable Inputs'!$B$31/1000000-B19) | C21: =MAX(0,'Editable Inputs'!$B$31/1000000-C19) | D21: Not backed by audited free cash flow.
A22: Equivalent annual market value per resident CAD | B22: =B19*1000000/B2 | C22: =C19*1000000/C2 | D22: Only a scenario value, not household cash.
A23: Additional electricity to data centres (TWh/year) | B23: =B6/1000 | C23: =C6/1000 | D23: E-mobility additional to data-centre and food electricity.
A24: Important: fossil parity is not free fuel | B24: =0 | C24: =0 | D24: Price parity means zero premium over fossil benchmark, not zero price.
A25: Fresh produce entitlement kg per resident-year | B25: ='Editable Inputs'!$B$19 | C25: ='Editable Inputs'!$B$19 | D25: Entitlement set by proponent, not household purchase.
A26: Seafood entitlement kg per resident-year | B26: ='Editable Inputs'!$B$22 | C26: ='Editable Inputs'!$B$22 | D26: Entitlement set by proponent, not household purchase.
A27: Fresh produce to residents t/year | B27: =B2*B25/1000 | C27: =C2*C25/1000 | D27: Population times 146 kg, no separate 50% crop-allocation input.
A28: Seafood to residents t/year | B28: =B2*B26/1000 | C28: =C2*C26/1000 | D28: Population times 46 kg, no separate 10% harvest input.
A29: Combined fresh-food entitlement t/year | B29: =SUM(B27:B28) | C29: =SUM(C27:C28) | D29: No double counting; fresh produce and seafood are separate.
A30: Share of modeled greenhouse harvest allocated | B30: =B27/'Editable Inputs'!$B$18 | C30: =C27/'Editable Inputs'!$B$18 | D30: Relative to illustrative 250,000 t/year harvest.
A31: Share of modeled aquaculture harvest allocated | B31: =B28/'Editable Inputs'!$B$21 | C31: =C28/'Editable Inputs'!$B$21 | D31: Relative to illustrative 120,000 t/year aquaculture.
A32: Greenhouse produce remaining t/year | B32: ='Editable Inputs'!$B$18*'Editable Inputs'!$B$36-B27 | C32: ='Editable Inputs'!$B$18*'Editable Inputs'!$B$36-C27 | D32: Surplus after illustrative marketable-grade pack-out.
A33: Aquaculture remaining t/year | B33: ='Editable Inputs'!$B$21*'Editable Inputs'!$B$37-B28 | C33: ='Editable Inputs'!$B$21*'Editable Inputs'!$B$37-C28 | D33: Surplus after assumed whole-animal to market-product yield.
A34: Food beneficiary market value CAD m | B34: =B13+B14 | C34: =C13+C14 | D34: Check = sum of food rows in main benefit schedule.
A35: Food fulfilment funding cost CAD m | B35: =B34*'Editable Inputs'!$B$24 | C35: =C34*'Editable Inputs'!$B$24 | D35: Conditional procurement/distribution funding at modeled cost factor.
A36: Share of marketable greenhouse food allocation | B36: =B27/('Editable Inputs'!$B$18*'Editable Inputs'!$B$36) | C36: =C27/('Editable Inputs'!$B$18*'Editable Inputs'!$B$36) | D36: Share of marketable (not gross harvest) fresh produce.
A37: Share of marketable seafood allocation | B37: =B28/('Editable Inputs'!$B$21*'Editable Inputs'!$B$37) | C37: =C28/('Editable Inputs'!$B$21*'Editable Inputs'!$B$37) | D37: Share of marketable (not liveweight) aquaculture output.

Sheet PUE Utilisation
A1: IT Utilisation | B1: PUE | C1: Facility TWh/year | D1: Captured heat TWh/year | E1: Potential end-use TWh/year | F1: Scope 2 Mt/y @50 kg/MWh
A2: 0.65 | B2: 1.1 | C2: ='Editable Inputs'!$B$32*A2*B2*8760/1000000 | D2: ='Editable Inputs'!$B$32*A2*'Editable Inputs'!$B$33*8760/1000000 | E2: =D2*'Editable Inputs'!$B$34 | F2: =C2*'Editable Inputs'!$B$35/1000
A3: 0.65 | B3: 1.15 | C3: ='Editable Inputs'!$B$32*A3*B3*8760/1000000 | D3: ='Editable Inputs'!$B$32*A3*'Editable Inputs'!$B$33*8760/1000000 | E3: =D3*'Editable Inputs'!$B$34 | F3: =C3*'Editable Inputs'!$B$35/1000
A4: 0.65 | B4: 1.3 | C4: ='Editable Inputs'!$B$32*A4*B4*8760/1000000 | D4: ='Editable Inputs'!$B$32*A4*'Editable Inputs'!$B$33*8760/1000000 | E4: =D4*'Editable Inputs'!$B$34 | F4: =C4*'Editable Inputs'!$B$35/1000
A5: 0.75 | B5: 1.1 | C5: ='Editable Inputs'!$B$32*A5*B5*8760/1000000 | D5: ='Editable Inputs'!$B$32*A5*'Editable Inputs'!$B$33*8760/1000000 | E5: =D5*'Editable Inputs'!$B$34 | F5: =C5*'Editable Inputs'!$B$35/1000
A6: 0.75 | B6: 1.15 | C6: ='Editable Inputs'!$B$32*A6*B6*8760/1000000 | D6: ='Editable Inputs'!$B$32*A6*'Editable Inputs'!$B$33*8760/1000000 | E6: =D6*'Editable Inputs'!$B$34 | F6: =C6*'Editable Inputs'!$B$35/1000
A7: 0.75 | B7: 1.3 | C7: ='Editable Inputs'!$B$32*A7*B7*8760/1000000 | D7: ='Editable Inputs'!$B$32*A7*'Editable Inputs'!$B$33*8760/1000000 | E7: =D7*'Editable Inputs'!$B$34 | F7: =C7*'Editable Inputs'!$B$35/1000
A8: 0.9 | B8: 1.1 | C8: ='Editable Inputs'!$B$32*A8*B8*8760/1000000 | D8: ='Editable Inputs'!$B$32*A8*'Editable Inputs'!$B$33*8760/1000000 | E8: =D8*'Editable Inputs'!$B$34 | F8: =C8*'Editable Inputs'!$B$35/1000
A9: 0.9 | B9: 1.15 | C9: ='Editable Inputs'!$B$32*A9*B9*8760/1000000 | D9: ='Editable Inputs'!$B$32*A9*'Editable Inputs'!$B$33*8760/1000000 | E9: =D9*'Editable Inputs'!$B$34 | F9: =C9*'Editable Inputs'!$B$35/1000
A10: 0.9 | B10: 1.3 | C10: ='Editable Inputs'!$B$32*A10*B10*8760/1000000 | D10: ='Editable Inputs'!$B$32*A10*'Editable Inputs'!$B$33*8760/1000000 | E10: =D10*'Editable Inputs'!$B$34 | F10: =C10*'Editable Inputs'!$B$35/1000

Sheet Food Entitlement Summary
A1: FOOD ENTITLEMENTS | B1: PER RESIDENT/YEAR | C1: PHASE 1 | D1: FULL PHASE 2
A2: Residents | C2: ='Two-phase Benefits'!B2 | D2: ='Two-phase Benefits'!C2
A3: Fresh produce kg | B3: ='Editable Inputs'!$B$19 | C3: ='Two-phase Benefits'!B25 | D3: ='Two-phase Benefits'!C25
A4: Seafood kg | B4: ='Editable Inputs'!$B$22 | C4: ='Two-phase Benefits'!B26 | D4: ='Two-phase Benefits'!C26
A5: Fresh produce allocated tonnes/year | C5: ='Two-phase Benefits'!B27 | D5: ='Two-phase Benefits'!C27
A6: Seafood allocated tonnes/year | C6: ='Two-phase Benefits'!B28 | D6: ='Two-phase Benefits'!C28
A7: Combined tonnes/year | C7: ='Two-phase Benefits'!B29 | D7: ='Two-phase Benefits'!C29
A8: Produce programme market value CAD m | C8: ='Two-phase Benefits'!B13 | D8: ='Two-phase Benefits'!C13
A9: Seafood market value CAD m | C9: ='Two-phase Benefits'!B14 | D9: ='Two-phase Benefits'!C14
A10: Produce share of proposed harvest | C10: ='Two-phase Benefits'!B30 | D10: ='Two-phase Benefits'!C30
A11: Seafood share of proposed harvest | C11: ='Two-phase Benefits'!B31 | D11: ='Two-phase Benefits'!C31
A12: Total benefit value CAD m | C12: ='Two-phase Benefits'!B19 | D12: ='Two-phase Benefits'!C19
A13: Produce share of marketable output | C13: ='Two-phase Benefits'!B36 | D13: ='Two-phase Benefits'!C36
A14: Seafood share of marketable output | C14: ='Two-phase Benefits'!B37 | D14: ='Two-phase Benefits'!C37

Sheet Sources and limits
A1: SOURCE / LIMITATION | B1: SUMMARY
A2: Statistics Canada B.C. 2021 Census | B2: 2.4 persons/household; source is provincial proxy, not 17-site census.
A3: BC Hydro public EV charging rates Apr 2026 | B3: L2 CAD 0.3083/kWh; fast CAD 0.3969/kWh before tax.
A4: Natural Resources Canada renewable hydrocarbon diesel | B4: Premium over petroleum varies with costs and fossil fuel prices.
A5: Digital Gardens 17-node published design | B5: 3,624.51 MW IT; 787,934 covered residents supplied by author.
A6: Vehicle benefits assumption | B6: Provision of a vehicle is an optional policy design input, not a confirmed offer.
A7: No free home electricity | B7: Explicit ZERO benefit to domestic electric meters; only free EV charging.
A8: Finance caveat | B8: Value to beneficiaries, actual funding, and cash flow must be audited separately.
A9: BC Ministry of Agriculture 2021 census profiles | B9: https://www2.gov.bc.ca/gov/content/industry/agriculture-seafood/statistics/census-of-agriculture
A10: Forage machinery reference | B10: https://doi.org/10.1007/s11367-023-02199-1
A11: ECCC diesel factor | B11: https://www.canada.ca/en/environment-climate-change/services/climate-change/pricing-pollution-how-it-will-work/output-based-pricing-system/federal-greenhouse-gas-offset-system/emission-factors-reference-values.html
A12: Farm fuel tax eligibility | B12: https://www2.gov.bc.ca/gov/content/taxes/sales-taxes/motor-fuel-carbon-tax/business/exemptions
A13: Key boundary | B13: Eight complete RDs are counted, allocated to 17 nodes without duplication; NOT complete municipal farm inventory.

Sheet Farm Coefficients
A1: SCENARIO INPUT / COMPONENT | B1: INPUT | C1: UNIT | D1: EMPIRICAL BASIS / STATUS
A2: Hay | B2: 30 | C2: L/ha/year | D2: Scenario 30; Canada forage literature 22–36 L/ha/y
A3: Other cropped land | B3: 65 | C3: L/ha/year | D3: Scenario; multiple field operations; not field survey
A4: Orchards, fruit, berries and nuts | B4: 130 | C4: L/ha/year | D4: Scenario; equipment, mowing, spraying, harvest
A5: Vegetables | B5: 150 | C5: L/ha/year | D5: Scenario; multiple cultivation passes
A6: Nursery, sod | B6: 100 | C6: L/ha/year | D6: Scenario, farm-specific variation
A7: Seeded pasture | B7: 25 | C7: L/ha/year | D7: Scenario; cultivation and mowing
A8: Natural pasture | B8: 1.5 | C8: L/ha/year | D8: Scenario; sparse visits on extensive grazing land
A9: Other farmland | B9: 3 | C9: L/ha/year | D9: Scenario; service roads and machinery
A10: Fixed per farm / livestock services | B10: 800 | C10: L/farm/year | D10: Scenario; supplementary service work; no measured sales
A11: Renewable - fossil price difference | B11: 0.25 | C11: CAD/L | D11: Unverified market parity price gap; positive-only
A12: Programme uptake | B12: 1 | C12: fraction | D12: Scenario: full replacement
A13: Diesel direct CO2 baseline | B13: 2.681 | C13: kg/L | D13: ECCC 2026 combustion factor, not lifecycle savings
... A16: Former total fuel allocation | B16: 100000000 | C16: L/year | D16: Unverified prior assumption, NOT measured volume

Sheet RD Agriculture
A1: 2021 census region | B1: Farms (#) | C1: Cropland ha | D1: Hay ha | E1: Fruit/berries ha | F1: Vegetables ha | G1: Nursery/sod ha | H1: Seeded pasture ha | I1: Natural pasture ha | J1: Other farmland ha | K1: Residual field ha | L1: Diesel estimated L/y | M1: Parity subsidy CAD/y | N1: Total farmland ha | O1: Source (official 2021 profile)
A2: Squamish-Lillooet | B2: 117 | C2: 2120 | D2: 912 | E2: 30 | F2: 40 | G2: 19 | H2: 498 | I2: 3136 | J2: 578 | K2: =MAX(0,C2-D2-E2-F2-G2) | L2: =D2*'Farm Coefficients'!$B$2+K2*'Farm Coefficients'!$B$3+E2*'Farm Coefficients'!$B$4+F2*'Farm Coefficients'!$B$5+G2*'Farm Coefficients'!$B$6+H2*'Farm Coefficients'!$B$7+I2*'Farm Coefficients'!$B$8+J2*'Farm Coefficients'!$B$9+B2*'Farm Coefficients'!$B$10 | M2: =L2*MAX(0,'Farm Coefficients'!$B$11)*'Farm Coefficients'!$B$12 | N2: 7526 | O2: https://www2.gov.bc.ca/assets/gov/farming-natural-resources-and-industry/agriculture-and-seafood/statistics/census/ag-in-brief/dec2024/cd/ag_in_brief_2021_-_cd_squamish-lillooet_-_december_2024_correction.pdf
A3: Thompson-Nicola | B3: 895 | C3: 28365 | D3: 7541 | E3: 51 | F3: 246 | G3: 5 | H3: 10427 | I3: 419904 | J3: 6103 | K3: =MAX(0,C3-D3-E3-F3-G3) | L3: =D3*'Farm Coefficients'!$B$2+K3*'Farm Coefficients'!$B$3+E3*'Farm Coefficients'!$B$4+F3*'Farm Coefficients'!$B$5+G3*'Farm Coefficients'!$B$6+H3*'Farm Coefficients'!$B$7+I3*'Farm Coefficients'!$B$8+J3*'Farm Coefficients'!$B$9+B3*'Farm Coefficients'!$B$10 | M3: =L3*MAX(0,'Farm Coefficients'!$B$11)*'Farm Coefficients'!$B$12 | N3: 516079 | O3: https://www2.gov.bc.ca/assets/gov/farming-natural-resources-and-industry/agriculture-and-seafood/statistics/census/ag-in-brief/dec2024/cd/ag_in_brief_2021_-_cd_thompson-nicola_-_december_2024_correction.pdf
A4: Columbia-Shuswap | B4: 510 | C4: 10170 | D4: 3265 | E4: 122 | F4: 57 | G4: 35 | H4: 1663 | I4: 8253 | J4: 1616 | K4: =MAX(0,C4-D4-E4-F4-G4) | L4: =D4*'Farm Coefficients'!$B$2+K4*'Farm Coefficients'!$B$3+E4*'Farm Coefficients'!$B$4+F4*'Farm Coefficients'!$B$5+G4*'Farm Coefficients'!$B$6+H4*'Farm Coefficients'!$B$7+I4*'Farm Coefficients'!$B$8+J4*'Farm Coefficients'!$B$9+B4*'Farm Coefficients'!$B$10 | M4: =L4*MAX(0,'Farm Coefficients'!$B$11)*'Farm Coefficients'!$B$12 | N4: 27052 | O4: https://www2.gov.bc.ca/assets/gov/farming-natural-resources-and-industry/agriculture-and-seafood/statistics/census/ag-in-brief/dec2024/cd/ag_in_brief_2021_-_cd_columbia-shuswap_-_december_2024_correction.pdf
A5: North Okanagan | B5: 972 | C5: 19666 | D5: 5411 | E5: 470 | F5: 133 | G5: 143 | H5: 2180 | I5: 32397 | J5: 2586 | K5: =MAX(0,C5-D5-E5-F5-G5) | L5: =D5*'Farm Coefficients'!$B$2+K5*'Farm Coefficients'!$B$3+E5*'Farm Coefficients'!$B$4+F5*'Farm Coefficients'!$B$5+G5*'Farm Coefficients'!$B$6+H5*'Farm Coefficients'!$B$7+I5*'Farm Coefficients'!$B$8+J5*'Farm Coefficients'!$B$9+B5*'Farm Coefficients'!$B$10 | M5: =L5*MAX(0,'Farm Coefficients'!$B$11)*'Farm Coefficients'!$B$12 | N5: 62415 | O5: https://www2.gov.bc.ca/assets/gov/farming-natural-resources-and-industry/agriculture-and-seafood/statistics/census/ag-in-brief/dec2024/cd/ag_in_brief_2021_-_cd_north_okanagan_-_december_2024_correction.pdf
A6: Central Okanagan | B6: 807 | C6: 6608 | D6: 705 | E6: 3879 | F6: 98 | G6: 377 | H6: 606 | I6: 11193 | J6: 1474 | K6: =MAX(0,C6-D6-E6-F6-G6) | L6: =D6*'Farm Coefficients'!$B$2+K6*'Farm Coefficients'!$B$3+E6*'Farm Coefficients'!$B$4+F6*'Farm Coefficients'!$B$5+G6*'Farm Coefficients'!$B$6+H6*'Farm Coefficients'!$B$7+I6*'Farm Coefficients'!$B$8+J6*'Farm Coefficients'!$B$9+B6*'Farm Coefficients'!$B$10 | M6: =L6*MAX(0,'Farm Coefficients'!$B$11)*'Farm Coefficients'!$B$12 | N6: 20888 | O6: https://www2.gov.bc.ca/assets/gov/farming-natural-resources-and-industry/agriculture-and-seafood/statistics/census/ag-in-brief/dec2024/cd/ag_in_brief_2021_-_cd_central_okanagan_-_december_2024_correction.pdf
A7: Okanagan-Similkameen | B7: 1231 | C7: 10558 | D7: 633 | E7: 7166 | F7: 282 | G7: 10 | H7: 1252 | I7: 48822 | J7: 2370 | K7: =MAX(0,C7-D7-E7-F7-G7) | L7: =D7*'Farm Coefficients'!$B$2+K7*'Farm Coefficients'!$B$3+E7*'Farm Coefficients'!$B$4+F7*'Farm Coefficients'!$B$5+G7*'Farm Coefficients'!$B$6+H7*'Farm Coefficients'!$B$7+I7*'Farm Coefficients'!$B$8+J7*'Farm Coefficients'!$B$9+B7*'Farm Coefficients'!$B$10 | M7: =L7*MAX(0,'Farm Coefficients'!$B$11)*'Farm Coefficients'!$B$12 | N7: 65516 | O7: https://www2.gov.bc.ca/assets/gov/farming-natural-resources-and-industry/agriculture-and-seafood/statistics/census/ag-in-brief/dec2024/cd/ag_in_brief_2021_-_cd_okanagan-similkameen_-_december_2024_correction.pdf
A8: Fraser Valley | B8: 2358 | C8: 36962 | D8: 10784 | E8: 6473 | F8: 1843 | G8: 1278 | H8: 2619 | I8: 14027 | J8: 4748 | K8: =MAX(0,C8-D8-E8-F8-G8) | L8: =D8*'Farm Coefficients'!$B$2+K8*'Farm Coefficients'!$B$3+E8*'Farm Coefficients'!$B$4+F8*'Farm Coefficients'!$B$5+G8*'Farm Coefficients'!$B$6+H8*'Farm Coefficients'!$B$7+I8*'Farm Coefficients'!$B$8+J8*'Farm Coefficients'!$B$9+B8*'Farm Coefficients'!$B$10 | M8: =L8*MAX(0,'Farm Coefficients'!$B$11)*'Farm Coefficients'!$B$12 | N8: 60350 | O8: https://www2.gov.bc.ca/assets/gov/farming-natural-resources-and-industry/agriculture-and-seafood/statistics/census/ag-in-brief/dec2024/cd/ag_in_brief_2021_-_cd_fraser_valley_-_december_2024_correction.pdf
A9: Greater Vancouver | B9: 2118 | C9: 24999 | D9: 5535 | E9: 8368 | F9: 2401 | G9: 677 | H9: 999 | I9: 2627 | J9: 4517 | K9: =MAX(0,C9-D9-E9-F9-G9) | L9: =D9*'Farm Coefficients'!$B$2+K9*'Farm Coefficients'!$B$3+E9*'Farm Coefficients'!$B$4+F9*'Farm Coefficients'!$B$5+G9*'Farm Coefficients'!$B$6+H9*'Farm Coefficients'!$B$7+I9*'Farm Coefficients'!$B$8+J9*'Farm Coefficients'!$B$9+B9*'Farm Coefficients'!$B$10 | M9: =L9*MAX(0,'Farm Coefficients'!$B$11)*'Farm Coefficients'!$B$12 | N9: 34360 | O9: https://www2.gov.bc.ca/assets/gov/farming-natural-resources-and-industry/agriculture-and-seafood/statistics/census/ag-in-brief/ag_in_brief_2021_-_cd_greater_vancouver.pdf
A10: TOTAL (all 8 regional districts) | B10: =SUM(B2:B9) | C10: =SUM(C2:C9) | D10: =SUM(D2:D9) | E10: =SUM(E2:E9) | F10: =SUM(F2:F9) | G10: =SUM(G2:G9) | H10: =SUM(H2:H9) | I10: =SUM(I2:I9) | ... N10: =SUM(N2:N9) | O10: Covers wider regions than only municipalities

Sheet 17 Community Allocation
A1: Community | B1: Regional district | C1: Attribution weight (assumed) | D1: Diesel L/year proxy | E1: Renewable-fuel parity CAD/year | F1: Evidence limitation
A2: Lillooet | B2: Squamish-Lillooet | C2: 1 | D2: =INDEX('RD Agriculture'!$L$2:$L$9,MATCH(B2,'RD Agriculture'!$A$2:$A$9,0))*C2 | E2: =D2*MAX(0,'Farm Coefficients'!$B$11)*'Farm Coefficients'!$B$12 | F2: Service allocation proxy; NOT city-level measured farm diesel
A3: Cache Creek | B3: Thompson-Nicola | C3: 0.15 | D3: =INDEX('RD Agriculture'!$L$2:$L$9,MATCH(B3,'RD Agriculture'!$A$2:$A$9,0))*C3 | E3: =D3*MAX(0,'Farm Coefficients'!$B$11)*'Farm Coefficients'!$B$12 | F3: Service allocation proxy; NOT city-level measured farm diesel
A4: Kamloops | B4: Thompson-Nicola | C4: 0.55 | D4: =INDEX('RD Agriculture'!$L$2:$L$9,MATCH(B4,'RD Agriculture'!$A$2:$A$9,0))*C4 | E4: =D4*MAX(0,'Farm Coefficients'!$B$11)*'Farm Coefficients'!$B$12 | F4: Service allocation proxy; NOT city-level measured farm diesel
A5: Chase | B5: Thompson-Nicola | C5: 0.3 | D5: =INDEX('RD Agriculture'!$L$2:$L$9,MATCH(B5,'RD Agriculture'!$A$2:$A$9,0))*C5 | E5: =D5*MAX(0,'Farm Coefficients'!$B$11)*'Farm Coefficients'!$B$12 | F5: Service allocation proxy; NOT city-level measured farm diesel
A6: Salmon Arm | B6: Columbia-Shuswap | C6: 1 | D6: =INDEX('RD Agriculture'!$L$2:$L$9,MATCH(B6,'RD Agriculture'!$A$2:$A$9,0))*C6 | E6: =D6*MAX(0,'Farm Coefficients'!$B$11)*'Farm Coefficients'!$B$12 | F6: Service allocation proxy; NOT city-level measured farm diesel
A7: Vernon | B7: North Okanagan | C7: 1 | D7: =INDEX('RD Agriculture'!$L$2:$L$9,MATCH(B7,'RD Agriculture'!$A$2:$A$9,0))*C7 | E7: =D7*MAX(0,'Farm Coefficients'!$B$11)*'Farm Coefficients'!$B$12 | F7: Service allocation proxy; NOT city-level measured farm diesel
A8: Kelowna | B8: Central Okanagan | C8: 0.75 | D8: =INDEX('RD Agriculture'!$L$2:$L$9,MATCH(B8,'RD Agriculture'!$A$2:$A$9,0))*C8 | E8: =D8*MAX(0,'Farm Coefficients'!$B$11)*'Farm Coefficients'!$B$12 | F8: Service allocation proxy; NOT city-level measured farm diesel
A9: West Kelowna | B9: Central Okanagan | C9: 0.25 | D9: =INDEX('RD Agriculture'!$L$2:$L$9,MATCH(B9,'RD Agriculture'!$A$2:$A$9,0))*C9 | E9: =D9*MAX(0,'Farm Coefficients'!$B$11)*'Farm Coefficients'!$B$12 | F9: Service allocation proxy; NOT city-level measured farm diesel
A10: Penticton | B10: Okanagan-Similkameen | C10: 0.45 | D10: =INDEX('RD Agriculture'!$L$2:$L$9,MATCH(B10,'RD Agriculture'!$A$2:$A$9,0))*C10 | E10: =D10*MAX(0,'Farm Coefficients'!$B$11)*'Farm Coefficients'!$B$12 | F10: Service allocation proxy; NOT city-level measured farm diesel
A11: Oliver | B11: Okanagan-Similkameen | C11: 0.3 | D11: =INDEX('RD Agriculture'!$L$2:$L$9,MATCH(B11,'RD Agriculture'!$A$2:$A$9,0))*C11 | E11: =D11*MAX(0,'Farm Coefficients'!$B$11)*'Farm Coefficients'!$B$12 | F11: Service allocation proxy; NOT city-level measured farm diesel
A12: Osoyoos | B12: Okanagan-Similkameen | C12: 0.25 | D12: =INDEX('RD Agriculture'!$L$2:$L$9,MATCH(B12,'RD Agriculture'!$A$2:$A$9,0))*C12 | E12: =D12*MAX(0,'Farm Coefficients'!$B$11)*'Farm Coefficients'!$B$12 | F12: Service allocation proxy; NOT city-level measured farm diesel
A13: Hope | B13: Fraser Valley | C13: 0.1 | D13: =INDEX('RD Agriculture'!$L$2:$L$9,MATCH(B13,'RD Agriculture'!$A$2:$A$9,0))*C13 | E13: =D13*MAX(0,'Farm Coefficients'!$B$11)*'Farm Coefficients'!$B$12 | F13: Service allocation proxy; NOT city-level measured farm diesel
... A18: Maple Ridge | B18: Greater Vancouver | C18: 1 | D18: =INDEX('RD Agriculture'!$L$2:$L$9,MATCH(B18,'RD Agriculture'!$A$2:$A$9,0))*C18 | E18: =D18*MAX(0,'Farm Coefficients'!$B$11)*'Farm Coefficients'!$B$12 | F18: Service allocation proxy; NOT city-level measured farm diesel
A19: TOTAL | C19: =SUM(C2:C18) | D19: =SUM(D2:D18) | E19: =SUM(E2:E18) | F19: Sum allocated exactly once across eight districts

Sheet Fuel Sensitivity
A1: Intensity multiplier | B1: Price premium CAD/L | C1: Diesel L/year | D1: Subsidy CAD/year | E1: Phase 1 CAD/year | F1: Status
A2: 0.5 | B2: 0.1 | C2: ='RD Agriculture'!$L$10*A2 | D2: =MAX(0,B2)*C2 | E2: =D2*'Editable Inputs'!$B$3 | F2: Scenario sensitivity; not market quotations
A3: 0.5 | B3: 0.25 | C3: ='RD Agriculture'!$L$10*A3 | D3: =MAX(0,B3)*C3 | E3: =D3*'Editable Inputs'!$B$3 | F3: Scenario sensitivity; not market quotations
A4: 0.5 | B4: 0.45 | C4: ='RD Agriculture'!$L$10*A4 | D4: =MAX(0,B4)*C4 | E4: =D4*'Editable Inputs'!$B$3 | F4: Scenario sensitivity; not market quotations
A5: 1 | B5: 0.1 | C5: ='RD Agriculture'!$L$10*A5 | D5: =MAX(0,B5)*C5 | E5: =D5*'Editable Inputs'!$B$3 | F5: Scenario sensitivity; not market quotations
A6: 1 | B6: 0.25 | C6: ='RD Agriculture'!$L$10*A6 | D6: =MAX(0,B6)*C6 | E6: =D6*'Editable Inputs'!$B$3 | F6: Scenario sensitivity; not market quotations
A7: 1 | B7: 0.45 | C7: ='RD Agriculture'!$L$10*A7 | D7: =MAX(0,B7)*C7 | E7: =D7*'Editable Inputs'!$B$3 | F7: Scenario sensitivity; not market quotations
A8: 1.6 | B8: 0.1 | C8: ='RD Agriculture'!$L$10*A8 | D8: =MAX(0,B8)*C8 | E8: =D8*'Editable Inputs'!$B$3 | F8: Scenario sensitivity; not market quotations
A9: 1.6 | B9: 0.25 | C9: ='RD Agriculture'!$L$10*A9 | D9: =MAX(0,B9)*C9 | E9: =D9*'Editable Inputs'!$B$3 | F9: Scenario sensitivity; not market quotations
A10: 1.6 | B10: 0.45 | C10: ='RD Agriculture'!$L$10*A10 | D10: =MAX(0,B10)*C10 | E10: =D10*'Editable Inputs'!$B$3 | F10: Scenario sensitivity; not market quotations

Sheet Agricultural Summary
A1: MEASURE / RECONCILIATION | B1: VALUE | C1: INTERPRETATION
A2: Count of linked 2021 census districts | B2: =COUNTA('RD Agriculture'!A2:A9) | C2: Regions include farmland outside host municipal boundaries
A3: Count of host communities | B3: =COUNTA('17 Community Allocation'!A2:A18) | C3: Site weights not observed farm distribution
A4: Farms in broader 8-RD area | B4: ='RD Agriculture'!B10 | C4: Farm count official 2021, not 2026
A5: Census farmland in broader 8-RD area (ha) | B5: ='RD Agriculture'!N10 | C5: Includes pasture/natural land; not all ploughed
A6: Farming machinery diesel SCREEN litres/year | B6: ='RD Agriculture'!L10 | C6: Assumptions, NOT volume sales
A7: Annual ag price-parity CAD/year | B7: ='RD Agriculture'!M10 | C7: Max(0, renewable-fossil premium) times replaced L
A8: Earlier unverified agriculture allocation L/year | B8: ='Farm Coefficients'!B16 | C8: Replaced by farm-sector bottom-up screen
A9: Old allocation less screening L/year | B9: =B8-B6 | C9: Should not be misconstrued as measured excess
A10: Full annual community beneficiary value CAD m | B10: ='Two-phase Benefits'!C19 | C10: Includes vehicle-provision optional scenario
A11: Annual program funding CAD m | B11: ='Two-phase Benefits'!C20 | C11: Finance requirement not audited cash-flow
A12: No free household electricity | B12: ='Two-phase Benefits'!C18 | C12: Confirmed zero
A13: Food 146/46-kg entitlements preserved | B13: ='Food Entitlement Summary'!D7 | C13: Tonnes of produce + seafood combined
A14: Fossil diesel direct combustion t CO2/year | B14: ='RD Agriculture'!L10*'Farm Coefficients'!B13/1000 | C14: Comparator only; fuel lifecycle reductions NOT calculated
